{
	"class" : {
		"majorVersion" : "Richo 4/12/2018 17:04",
		"minorVersion" : "Richo 4/12/2018 17:04",
		"rsCoroutineState" : "Richo 12/28/2016 17:16",
		"rsError" : "Richo 10/21/2014 19:26",
		"rsFreeRAM" : "Richo 1/11/2018 12:39",
		"rsGlobalValue" : "Richo 8/31/2016 16:54",
		"rsPinValue" : "Richo 10/21/2014 19:26",
		"rsProfile" : "Richo 3/30/2016 17:02",
		"rsSerialTunnel" : "Richo 4/17/2018 08:17",
		"rsTickingScripts" : "Richo 5/8/2017 12:08",
		"rsTrace" : "Richo 12/21/2016 14:48" },
	"instance" : {
		"connectOnPort:" : "Richo 8/24/2016 18:14",
		"connectOnSocket:" : "Richo 8/24/2016 18:14",
		"currentProgram" : "Richo 5/20/2017 16:51",
		"debuggerOn:" : "Richo 1/9/2017 06:18",
		"disconnect" : "Richo 8/10/2015 10:19",
		"freeArduinoRAM" : "Richo 2/5/2018 18:46",
		"freeUziRAM" : "Richo 2/5/2018 18:54",
		"getGlobal:" : "Richo 1/9/2018 18:46",
		"getGlobalReport:" : "Richo 10/9/2016 18:20",
		"getPinMode:" : "Richo 10/29/2014 16:55",
		"getPinReport:" : "Richo 10/9/2016 18:17",
		"getPinValue:" : "Richo 10/13/2016 11:24",
		"initialize" : "Richo 5/8/2017 12:19",
		"install:" : "Richo 7/17/2016 19:21",
		"installCurrentProgram" : "Richo 11/9/2016 16:29",
		"isConnected" : "Richo 10/21/2014 14:42",
		"isTicking:" : "Richo 5/8/2017 12:46",
		"keepAlive" : "Richo 7/17/2016 19:21",
		"keepAliveTime" : "Richo 4/12/2018 07:59",
		"pinsReporting" : "Richo 10/4/2016 12:23",
		"portName" : "Richo 8/4/2015 18:25",
		"privateConnectOn:usingSerial:" : "Richo 4/13/2018 13:21",
		"privateDisconnect" : "Richo 10/13/2016 11:14",
		"processCoroutineState" : "Richo 5/21/2017 11:00",
		"processError" : "Richo 4/13/2018 12:52",
		"processFreeRAM" : "Richo 4/13/2018 13:10",
		"processGlobalValue" : "Richo 5/21/2017 11:04",
		"processInput" : "Richo 4/17/2018 08:17",
		"processPinValue" : "Richo 8/24/2016 18:06",
		"processProfile" : "Richo 4/13/2018 13:01",
		"processSerialTunnel" : "Richo 4/17/2018 08:24",
		"processTickingScripts" : "Richo 5/8/2017 13:02",
		"processTrace" : "Richo 4/13/2018 13:11",
		"requestConnection" : "Richo 4/12/2018 18:27",
		"run:" : "Richo 10/6/2016 10:38",
		"runOnce:" : "Richo 8/18/2016 20:29",
		"scripts" : "Richo 12/31/2016 19:48",
		"send:" : "Richo 7/17/2016 19:20",
		"sendPinsReporting" : "Richo 8/10/2015 11:16",
		"setBreakCount:value:" : "Richo 12/28/2016 13:42",
		"setGlobal:report:" : "Richo 1/9/2018 19:02",
		"setGlobal:value:" : "Richo 1/9/2018 19:02",
		"setPin:mode:" : "Richo 7/17/2016 19:21",
		"setPin:report:" : "Richo 7/17/2016 19:23",
		"setPin:value:" : "Richo 7/17/2016 19:23",
		"sourceCode" : "Richo 12/31/2016 20:30",
		"startKeepAliveProcess" : "Richo 8/10/2015 10:12",
		"startProfiling" : "Richo 7/17/2016 19:23",
		"startReporting" : "Richo 7/17/2016 19:22",
		"startSteppingProcess" : "Richo 8/10/2015 10:12",
		"step" : "Richo 10/13/2016 11:12",
		"stepTime" : "Richo 10/21/2014 14:12",
		"stopKeepAliveProcess" : "Richo 8/10/2015 10:15",
		"stopProfiling" : "Richo 7/17/2016 19:24",
		"stopReporting" : "Richo 7/17/2016 19:24",
		"stopSteppingProcess" : "Richo 10/21/2014 14:11",
		"variables" : "Richo 1/9/2018 19:00" } }
