{
	"class" : {
		 },
	"instance" : {
		"argumentList" : "Richo 4/8/2017 12:10",
		"assignment" : "Richo 12/27/2016 22:19",
		"binaryMessage" : "Richo 3/26/2017 10:09",
		"binarySelector" : "Richo 12/22/2016 15:34",
		"binarySend" : "Richo 3/26/2017 10:22",
		"binaryTail" : "Richo 12/22/2016 15:12",
		"block" : "Richo 4/8/2017 12:06",
		"comments" : "Richo 12/22/2016 12:30",
		"conditional:selector:arguments:" : "Richo 5/6/2017 19:57",
		"constant" : "Richo 12/27/2016 22:24",
		"digits" : "Richo 12/22/2016 12:00",
		"expression" : "Richo 4/6/2017 18:15",
		"flatten:tail:" : "Richo 12/22/2016 15:04",
		"float" : "Richo 12/22/2016 14:43",
		"forbiddenCharacters" : "Richo 12/22/2016 12:14",
		"identifier" : "Richo 12/22/2016 14:54",
		"integer" : "Richo 12/22/2016 14:43",
		"keywordMessage" : "Richo 3/26/2017 10:08",
		"keywordPair" : "Richo 12/22/2016 15:13",
		"keywordSelector" : "Richo 12/22/2016 15:34",
		"keywordSend" : "Richo 3/26/2017 10:22",
		"literal" : "Richo 12/22/2016 14:11",
		"loop:selector:arguments:" : "Richo 5/6/2017 20:00",
		"message:args:token:" : "Richo 3/26/2017 10:37",
		"number" : "Richo 12/27/2016 22:22",
		"operand" : "Richo 3/26/2017 20:52",
		"primitiveForSelector:" : "Richo 3/24/2017 17:40",
		"primitiveForSpecialVariable:" : "Richo 3/26/2017 17:08",
		"return" : "Richo 4/6/2017 19:24",
		"script" : "Richo 12/30/2016 15:08",
		"scriptName" : "Richo 3/24/2017 11:09",
		"scriptReference" : "Richo 3/26/2017 19:46",
		"scripting:selector:arguments:" : "Richo 5/6/2017 19:59",
		"send:messages:token:" : "Richo 3/26/2017 10:34",
		"separator" : "Richo 12/22/2016 14:37",
		"specialMessageSend:selector:arguments:" : "Richo 5/6/2017 19:55",
		"specialVariable" : "Richo 4/6/2017 19:25",
		"start" : "Richo 12/31/2016 14:22",
		"statement" : "Richo 12/22/2016 14:26",
		"statements" : "Richo 12/22/2016 15:31",
		"subexpression" : "Richo 12/22/2016 14:09",
		"tickingRate" : "Richo 12/27/2016 22:28",
		"tickingState" : "Richo 12/22/2016 14:48",
		"unaryMessage" : "Richo 3/26/2017 10:09",
		"unarySelector" : "Richo 12/22/2016 12:12",
		"unarySend" : "Richo 3/26/2017 10:22",
		"unaryTail" : "Richo 12/22/2016 15:05",
		"variable" : "Richo 12/27/2016 22:31",
		"variableDefinition" : "Richo 12/27/2016 22:30",
		"ws" : "Richo 12/22/2016 14:37" } }
